ironaai/__init__.py
ironaai/_utils.py
ironaai/callbacks.py
ironaai/exceptions.py
ironaai/llms/__init__.py
ironaai/llms/client.py
ironaai/llms/config.py
ironaai/llms/providers.py
ironaai/llms/request.py
ironaai/metrics/__init__.py
ironaai/metrics/metric.py
ironaai/metrics/request.py
ironaai/prompts.py
ironaai/settings.py
ironaai/toolkit/__init__.py
ironaai/toolkit/custom_router.py
ironaai/types.py
ironaai-0.1.12.dist-info/METADATA
ironaai-0.1.12.dist-info/WHEEL
ironaai-0.1.12.dist-info/RECORD
