Metadata-Version: 2.1
Name: ironaai
Version: 0.1.12
Summary: Irona AI Python SDK
Home-page: https://irona.ai/
Author: Irona AI
Author-email: support@irona.ai
Requires-Python: >=3.10,<3.13
Classifier: Programming Language :: Python :: 3
Classifier: Programming Language :: Python :: 3.10
Classifier: Programming Language :: Python :: 3.11
Classifier: Programming Language :: Python :: 3.12
Provides-Extra: create
Requires-Dist: aiohttp (>=3.9.3,<4.0.0)
Requires-Dist: langchain (>=0.2.7) ; extra == "create"
Requires-Dist: langchain-anthropic (>=0.1.20,<0.2.0) ; extra == "create"
Requires-Dist: langchain-cohere (>=0.1.9,<0.2.0) ; extra == "create"
Requires-Dist: langchain-community (>=0.2.16,<0.3.0) ; extra == "create"
Requires-Dist: langchain-google-genai (>=1.0.7) ; extra == "create"
Requires-Dist: langchain-mistralai (>=0.1.10,<0.2.0) ; extra == "create"
Requires-Dist: langchain-openai (>=0.1.16,<0.2.0) ; extra == "create"
Requires-Dist: langchain-together (>=0.1.4,<0.2.0) ; extra == "create"
Requires-Dist: litellm (>=1.30.0,<2.0.0)
Requires-Dist: pandas (>=2.2.2,<3.0.0)
Requires-Dist: pydantic-partial (>=0.5.5,<0.6.0)
Requires-Dist: python-dotenv (>=1.0.1,<2.0.0)
Requires-Dist: requests (>=2.31)
Project-URL: Documentation, https://ironaai.mintlify.app/
Project-URL: Repository, https://github.com/Irona-AI/ironaai-python
